ocifs/__init__.py
ocifs/core.py
ocifs/errors.py
ocifs/utils.py
ocifs/data_lake/__init__.py
ocifs/data_lake/lake_mount.py
ocifs/data_lake/lake_sharing_client.py
ocifs/data_lake/lake_sharing_object_storage_client.py
ocifs/data_lake/lakehouse.py
ocifs/data_lake/lakehouse_client.py
ocifs/data_lake/managed_prefix_collection.py
ocifs/data_lake/managed_prefix_summary.py
ocifs/data_lake/mount_specification.py
ocifs/data_lake/par_response.py
ocifs/data_lake/rename_object_details.py
ocifs/tests/__init__.py
ocifs/tests/test-requirements.txt
ocifs/tests/test_integration.py
ocifs/tests/test_integration_lake.py
ocifs/tests/test_spec.py
ocifs/tests/test_spec_lake.py
ocifs-1.3.4.dist-info/licenses/LICENSE.txt
ocifs-1.3.4.dist-info/WHEEL
ocifs-1.3.4.dist-info/METADATA
ocifs-1.3.4.dist-info/RECORD
