Metadata-Version: 2.4
Name: ocifs
Version: 1.3.4
Summary: Convenient filesystem interface over Oracle Cloud's Object Storage
Keywords: Oracle Cloud Infrastructure,OCI,Object Storage
Author: Oracle Cloud Infrastructure Data Science
Maintainer-email: Allen Hosler <allen.hosler@oracle.com>
Requires-Python: >=3.6
Classifier: Development Status :: 5 - Production/Stable
Classifier: Intended Audience :: Developers
Classifier: License :: OSI Approved :: Universal Permissive License (UPL)
Classifier: Operating System :: OS Independent
Classifier: Programming Language :: Python :: 3.6
Classifier: Programming Language :: Python :: 3.7
Classifier: Programming Language :: Python :: 3.8
Classifier: Programming Language :: Python :: 3.9
Classifier: Programming Language :: Python :: 3.10
Classifier: Programming Language :: Python :: 3.11
Classifier: Programming Language :: Python :: 3.12
Classifier: Programming Language :: Python :: 3.13
Classifier: Programming Language :: Python :: 3.14
License-File: LICENSE.txt
Requires-Dist: fsspec>=0.8.7
Requires-Dist: oci>=2.43.1
Requires-Dist: requests
Project-URL: Documentation, https://ocifs.readthedocs.io/en/latest/index.html
Project-URL: Github, https://github.com/oracle/ocifs
